# 虚拟机指令说明

```
R() 表示这是一个寄存器索引；
RK() 表示这是一个寄存器索引或者常量表索引；
Kst() 表示这是一个常量表索引；
```

指令结构：

| 6bit   | 8bit | 9bit | 9bit |
| ------ | ---- | ---- | ---- |
| opcode | A    | B    | C    |



| name    | args | des          |
| ------- | ---- | ------------ |
| OP_MOVE | A B  | R(A) := R(B) |

- A 存放B寄存器的值

```
local a = 1
local b = a

1	[1]	LOADK    	0 -1	; 1
2	[2]	MOVE     	1 0
```

| name     | args | des             |
| -------- | ---- | --------------- |
| OP_LOADK | A Bx | R(A) := Kst(Bx) |

- A 存放目标值的寄存器；
- Bx 常量表的索引；

```
local a = 1

1	[1]	LOADK    	0 -1	; 1
```

| name        | args  | des                          |
| ----------- | ----- | ---------------------------- |
| OP_SETTABUP | A B C | `UpValue[A][RK(B)] := RK(C)` |

- A 存放上值索引的寄存器；
- B 把从上值中A为索引取出来的 table 的索引
- C 要存放到上值中的值；

```
local a = {}
function f( ... )
	a[1] = 2
end

1	[1]	NEWTABLE 	0 0 0
2	[3]	SETTABUP 	0 -1 -2	; a 1 2
```



| name        | args | des                |
| ----------- | ---- | ------------------ |
| OP_SETUPVAL | A B  | UpValue[B] := R(A) |

将寄存器 A 的值放入上值表 key = B 中。

```
local a = 1
function f( ... )
	a = 2
end

1	[1]	LOADK    	0 -1	; 1
2	[3]	LOADK    	0 -1	; 2
3	[3]	SETUPVAL 	0 0	; a
```



| name    | args  | des                                      |
| ------- | ----- | ---------------------------------------- |
| OP_CALL | A B C | R(A), ... ,R(A+C-2) := R(A)(R(A+1), ... ,R(A+B-1)) |

- A 存放函数主体；
- B B-1表示参数个数，参数是(A + 1, B)；如果参数是变长的，则B=0，参数是(A+1 - 栈顶)；
- C 函数的返回值会存放在(A, C - 1)的寄存器上，如果C=0，则返回值变长；

| name       | args | des                         |
| ---------- | ---- | --------------------------- |
| OP_CLOSURE | A Bx | R(A) := closure(KPROTO[Bx]) |

- A 根据Proto创建closure存放；
- Bx 父函数原型Proto->p->p的索引；


| name      | args | des                                  |
| --------- | ---- | ------------------------------------ |
| OP_VARARG | A B  | R(A), R(A+1), ..., R(A+B-2) = vararg |

- 拷贝B-1个参数到从 A 开始的寄存器中，不足用 nil 补充；如果 B = 0，则拷贝实际参数数量；